{
   "description":"<p>Uma batida impressionante aconteceu no último mês na cidade de New Paris, no estado do Indiana, Estados Unidos. Uma limusine ficou presa na passagem de veículos&#8230;</p>\n<p>The post <a rel=\"nofollow\" href=\"http://www.minutoseguros.com.br/blog/carro/trem-limusine-seguro-auto-cobre/\">Trem atinge limusine: o seguro auto cobre?</a> appeared first on <a rel=\"nofollow\" href=\"http://www.minutoseguros.com.br/blog\">Blog Minuto</a>.</p>\n",
   "title":"Trem atinge limusine: o seguro auto cobre?",
   "content":"Uma batida impressionante aconteceu no último mês na cidade de New Paris, no estado do Indiana, Estados Unidos.",
   "html":"<p><img class=\"alignright  wp-image-15138\" src=\"/blog/wp-content/uploads/2015/08/limusine-trem.jpg\" alt=\"Limusine x trem\" width=\"246\" height=\"172\" />Uma batida impressionante aconteceu no último mês na cidade de New Paris, no estado do Indiana, Estados Unidos.</p>\n",
   "link":"http://www.minutoseguros.com.br/blog/carro/trem-limusine-seguro-auto-cobre/",
   "published_at":"2015-08-05"
}
